{
  "surah_no": 82,
  "ar_name": "الإنفطار",
  "bn_name": "আল-ইনফিতার",
  "en_name": "Al-Infitar",
  "ayahs": [
    {
      "ayah_no": 1,
      "arabic": "اِذَا  السَّمَآءُ  انۡفَطَرَتۡ ۙ﴿۱﴾ ",
      "bn": "যখন আকাশ ফেটে যাবে।",
      "words": []
    },
    {
      "ayah_no": 2,
      "arabic": "وَ  اِذَا الۡکَوَاکِبُ انۡتَثَرَتۡ ۙ﴿۲﴾ ",
      "bn": "আর যখন তারকারাজি বিক্ষিপ্ত হবে।",
      "words": []
    },
    {
      "ayah_no": 3,
      "arabic": "وَ  اِذَا الۡبِحَارُ فُجِّرَتۡ ﴿ۙ۳﴾ ",
      "bn": "আর যখন সাগরগুলো বিস্ফোরিত হবে।",
      "words": []
    },
    {
      "ayah_no": 4,
      "arabic": "وَ  اِذَا الۡقُبُوۡرُ بُعۡثِرَتۡ ۙ﴿۴﴾ ",
      "bn": "আর যখন কবরগুলো উন্মোচিত হবে।",
      "words": []
    },
    {
      "ayah_no": 5,
      "arabic": "عَلِمَتۡ نَفۡسٌ مَّا قَدَّمَتۡ وَ اَخَّرَتۡ ؕ﴿۵﴾ ",
      "bn": "প্রাণ জানতে পারবে যা সে আগে পাঠিয়েছে ও পিছনে রেখে গিয়েছে।",
      "words": []
    },
    {
      "ayah_no": 6,
      "arabic": "یٰۤاَیُّہَا  الۡاِنۡسَانُ مَا غَرَّکَ بِرَبِّکَ الۡکَرِیۡمِ ۙ﴿۶﴾ ",
      "bn": "ওহে মানুষ! কিসে তোমাকে তোমার মহান রবের ব্যাপারে বিভ্রান্ত করেছে! ",
      "words": []
    },
    {
      "ayah_no": 7,
      "arabic": "الَّذِیۡ خَلَقَکَ فَسَوّٰىکَ فَعَدَلَکَ ۙ﴿۷﴾ ",
      "bn": "যিনি তোমাকে সৃষ্টি করেছেন। এরপর তোমাকে সুবিন্যস্ত করেছেন। তারপর তোমাকে সুষম করেছেন।",
      "words": []
    },
    {
      "ayah_no": 8,
      "arabic": "فِیۡۤ  اَیِّ صُوۡرَۃٍ  مَّا شَآءَ  رَکَّبَکَ ؕ﴿۸﴾ ",
      "bn": "তিনি যে আকৃতির মধ্যে যেভাবে চেয়েছেন তোমাকে গঠন করেছেন।",
      "words": []
    },
    {
      "ayah_no": 9,
      "arabic": "کَلَّا  بَلۡ تُکَذِّبُوۡنَ بِالدِّیۡنِ ۙ﴿۹﴾ ",
      "bn": "কখনও নয়, বরং তোমরা দ্বীনকে মিথ্যাপ্রতিপন্ন করছ।",
      "words": []
    },
    {
      "ayah_no": 10,
      "arabic": "وَ  اِنَّ عَلَیۡکُمۡ  لَحٰفِظِیۡنَ ﴿ۙ۱۰﴾ ",
      "bn": "আর নিশ্চয়ই তোমাদের ওপর অবশ্যই পর্যবেক্ষক দল রয়েছে।",
      "words": []
    },
    {
      "ayah_no": 11,
      "arabic": "کِرَامًا  کَاتِبِیۡنَ ﴿ۙ۱۱﴾ ",
      "bn": "সম্মানিত লেখকবৃন্দ।",
      "words": []
    },
    {
      "ayah_no": 12,
      "arabic": "یَعۡلَمُوۡنَ مَا تَفۡعَلُوۡنَ ﴿۱۲﴾ ",
      "bn": "তারা জানে যা তোমরা করো।",
      "words": []
    },
    {
      "ayah_no": 13,
      "arabic": "اِنَّ  الۡاَبۡرَارَ لَفِیۡ نَعِیۡمٍ ﴿ۚ۱۳﴾ ",
      "bn": "নিশ্চয়ই পুণ্যবানরা থাকবে অবশ্যই নাঈমের মধ্যে।",
      "words": []
    },
    {
      "ayah_no": 14,
      "arabic": "وَ  اِنَّ  الۡفُجَّارَ لَفِیۡ جَحِیۡمٍ ﴿ۚۖ۱۴﴾ ",
      "bn": "আর নিশ্চয়ই পাপাচারীরা থাকবে অবশ্যই জাহিমের মধ্যে।",
      "words": []
    },
    {
      "ayah_no": 15,
      "arabic": "یَّصۡلَوۡنَہَا یَوۡمَ الدِّیۡنِ ﴿۱۵﴾ ",
      "bn": "সেখানে তারা প্রবেশ করবে কর্মফল দিনে।",
      "words": []
    },
    {
      "ayah_no": 16,
      "arabic": "وَ مَا ہُمۡ عَنۡہَا بِغَآئِبِیۡنَ ﴿ؕ۱۶﴾  ",
      "bn": "আর না তারা সেটার ক্ষেত্রে অনুপস্থিত।",
      "words": []
    },
    {
      "ayah_no": 17,
      "arabic": "وَ مَاۤ  اَدۡرٰىکَ مَا یَوۡمُ الدِّیۡنِ ﴿ۙ۱۷﴾ ",
      "bn": "এবং কিসে তোমাকে জানাবে, কর্মফল দিন কী?",
      "words": []
    },
    {
      "ayah_no": 18,
      "arabic": "ثُمَّ  مَاۤ  اَدۡرٰىکَ مَا یَوۡمُ الدِّیۡنِ ﴿ؕ۱۸﴾ ",
      "bn": "পুনশ্চ, কিসে তোমাকে জানাবে, কর্মফল দিন কী?",
      "words": []
    },
    {
      "ayah_no": 19,
      "arabic": "یَوۡمَ لَا تَمۡلِکُ نَفۡسٌ لِّنَفۡسٍ شَیۡئًا ؕ وَ الۡاَمۡرُ  یَوۡمَئِذٍ  لِّلّٰہِ ﴿٪۱۹﴾ ",
      "bn": "যেদিন কোনো প্রাণ কোনো প্রাণের কোনোকিছুরই অধিকারী হবে না এবং কতৃর্ত্ব সেদিন আল্লাহরই জন্য।",
      "words": []
    }
  ]
}